AUTHORS
INSTALL
LICENSE
MANIFEST.in
NOTICE
README
requirements.txt
setup.cfg
setup.py
docs/Makefile
docs/conf.py
docs/configuration.rst
docs/faq.rst
docs/index.rst
docs/installation.rst
docs/introduction.rst
docs/make.bat
docs/usage.rst
src/django_mysql_manager.egg-info/PKG-INFO
src/django_mysql_manager.egg-info/SOURCES.txt
src/django_mysql_manager.egg-info/dependency_links.txt
src/django_mysql_manager.egg-info/not-zip-safe
src/django_mysql_manager.egg-info/top_level.txt
src/mysql_manager/__init__.py
src/mysql_manager/actions.py
src/mysql_manager/admin.py
src/mysql_manager/forms.py
src/mysql_manager/managers.py
src/mysql_manager/models.py
src/mysql_manager/settings.py
src/mysql_manager/signal_cb.py
src/mysql_manager/tests.py
src/mysql_manager/management/__init__.py
src/mysql_manager/management/commands/__init__.py
src/mysql_manager/management/commands/generate_sql_statement_for_admin_user.py
src/mysql_manager/migrations/0001_initial.py
src/mysql_manager/migrations/__init__.py